{
  "mode": "bubble-self-realization.v1",
  "realizationId": "self-realization:bubble:examples/memory-seal.bubble::root:MemorySeal",
  "governingWillId": "world-will:4",
  "clockAssumption": "no-universal-clock",
  "stateSource": "authored-initial",
  "sourceContinuationId": null,
  "currentState": {
    "memory": "open"
  },
  "status": "realized",
  "candidates": [
    {
      "candidateId": "candidate:preserve:bubble:examples/memory-seal.bubble::root:MemorySeal",
      "kind": "preserve",
      "transformationId": null,
      "transformationName": "Preserve",
      "reversibility": "identity",
      "ordering": "none",
      "topology": "single",
      "identityOutcome": "open",
      "effectId": null,
      "effectKind": null,
      "effectRequirement": null,
      "consequence": "none",
      "eligible": true,
      "stateBefore": {
        "memory": "open"
      },
      "stateAfter": {
        "memory": "open"
      },
      "worldWillEvaluation": {
        "evaluationId": "semantic-evaluation:world-will:4",
        "subjectKind": "world-will",
        "subjectId": "world-will:4",
        "name": "world will",
        "sourceLine": 4,
        "description": "realization.name = \"Seal\"",
        "expression": "realization.name = \"Seal\"",
        "status": "violated",
        "basis": [
          "executable-semantic-checker",
          "world-will-violated"
        ],
        "explanation": "World will criterion is violated by the current executable semantic environment."
      },
      "admittedByWorldWill": false,
      "selected": false,
      "description": "Preserve keeps the authored world state invariant and introduces no causal order or history arrow."
    },
    {
      "candidateId": "candidate:transform:9:Seal",
      "kind": "transform",
      "transformationId": "transform:9:Seal",
      "transformationName": "Seal",
      "reversibility": "irreversible",
      "ordering": "committed-history",
      "topology": "single",
      "identityOutcome": "preserved",
      "effectId": "effect:8:commit",
      "effectKind": "commit",
      "effectRequirement": "required",
      "consequence": "history-commit",
      "eligible": true,
      "stateBefore": {
        "memory": "open"
      },
      "stateAfter": {
        "memory": "sealed"
      },
      "worldWillEvaluation": {
        "evaluationId": "semantic-evaluation:world-will:4",
        "subjectKind": "world-will",
        "subjectId": "world-will:4",
        "name": "world will",
        "sourceLine": 4,
        "description": "realization.name = \"Seal\"",
        "expression": "realization.name = \"Seal\"",
        "status": "satisfied",
        "basis": [
          "executable-semantic-checker",
          "world-will-satisfied"
        ],
        "explanation": "World will criterion is satisfied by the current executable semantic environment."
      },
      "admittedByWorldWill": true,
      "selected": true,
      "description": "Transform Seal is available from authored state memory=\"open\" and projects memory=\"sealed\"."
    }
  ],
  "selectedCandidateIds": [
    "candidate:transform:9:Seal"
  ],
  "continuations": [
    {
      "continuationId": "continuation:self-realization:bubble:examples/memory-seal.bubble::root:MemorySeal:candidate:transform:9:Seal",
      "candidateId": "candidate:transform:9:Seal",
      "transformationId": "transform:9:Seal",
      "state": {
        "memory": "sealed"
      },
      "reversibility": "irreversible",
      "ordering": "committed-history",
      "topology": "single",
      "consequence": "history-commit",
      "createsHistoryArrow": true
    }
  ],
  "obligationConflicts": [],
  "description": "World will world-will:4 selects Seal as the sole admitted self-realization."
}
